muffin_rest/__init__.py
muffin_rest/api.py
muffin_rest/errors.py
muffin_rest/filters.py
muffin_rest/handler.py
muffin_rest/limits.py
muffin_rest/marshmallow.py
muffin_rest/mongo/__init__.py
muffin_rest/mongo/filters.py
muffin_rest/mongo/schema.py
muffin_rest/mongo/sorting.py
muffin_rest/mongo/types.py
muffin_rest/mongo/utils.py
muffin_rest/openapi.py
muffin_rest/options.py
muffin_rest/peewee/__init__.py
muffin_rest/peewee/filters.py
muffin_rest/peewee/handler.py
muffin_rest/peewee/openapi.py
muffin_rest/peewee/options.py
muffin_rest/peewee/schemas.py
muffin_rest/peewee/sorting.py
muffin_rest/peewee/types.py
muffin_rest/peewee/utils.py
muffin_rest/py.typed
muffin_rest/redoc.html
muffin_rest/schemas.py
muffin_rest/sorting.py
muffin_rest/sqlalchemy/__init__.py
muffin_rest/sqlalchemy/filters.py
muffin_rest/sqlalchemy/sorting.py
muffin_rest/sqlalchemy/types.py
muffin_rest/swagger.html
muffin_rest/types.py
muffin_rest/utils.py
muffin_rest-13.0.3.dist-info/METADATA
muffin_rest-13.0.3.dist-info/WHEEL
muffin_rest-13.0.3.dist-info/licenses/LICENSE
muffin_rest-13.0.3.dist-info/RECORD
