Metadata-Version: 2.4
Name: muffin-rest
Version: 13.0.3
Summary: The package provides enhanced support for writing REST APIs with Muffin framework
License: MIT
License-File: LICENSE
Keywords: rest,api,muffin,asgi,asyncio,trio
Author: Kirill Klenov
Author-email: horneds@gmail.com
Requires-Python: >=3.10,<4.0
Classifier: Development Status :: 5 - Production/Stable
Classifier: Framework :: AsyncIO
Classifier: Framework :: Trio
Classifier: Intended Audience :: Developers
Classifier: License :: OSI Approved :: MIT License
Classifier: Programming Language :: Python
Classifier: Programming Language :: Python :: 3
Classifier: Programming Language :: Python :: 3.10
Classifier: Programming Language :: Python :: 3.11
Classifier: Programming Language :: Python :: 3.12
Classifier: Programming Language :: Python :: 3.13
Classifier: Programming Language :: Python :: 3.14
Classifier: Topic :: Internet :: WWW/HTTP
Provides-Extra: peewee
Provides-Extra: sqlalchemy
Provides-Extra: yaml
Requires-Dist: apispec (>=6,<7)
Requires-Dist: marshmallow (>=3,<4)
Requires-Dist: marshmallow-peewee ; extra == "peewee"
Requires-Dist: marshmallow-sqlalchemy ; extra == "sqlalchemy"
Requires-Dist: muffin
Requires-Dist: muffin-databases ; extra == "sqlalchemy"
Requires-Dist: muffin-peewee-aio ; extra == "peewee"
Requires-Dist: pyyaml ; extra == "yaml"
Requires-Dist: sqlalchemy ; extra == "sqlalchemy"
Project-URL: Homepage, https://github.com/klen/muffin-rest
Project-URL: Repository, https://github.com/klen/muffin-rest
